{
  "data": {
    "type": "dois",
    "attributes": {
      "doi": "",
      "prefix": "10.48322",
      "suffix": "",
      "url": "https://hpde.io/NASA/NumericalData/MESSENGER/MAG/PT0.05S.html",
      "types": {
        "ris": "DATA",
        "bibtex": "misc",
        "citeproc": "dataset",
        "schemaOrg": "Dataset",
        "resourceTypeGeneral": "Dataset"
      },
      "creators": [
        {
          "name": "Solomon, Sean C.",
          "nameType": "Personal",
          "givenName": "Sean C.",
          "familyName": "Solomon",
          "affiliation": [
            {
              "name": "Carnegie Institution of Washington",
              "schemeUri": "https://ror.org",
              "affiliationIdentifier": "https://ror.org/ZZZ",
              "affiliationIdentifierScheme": "ROR"
            }
          ],
          "nameIdentifiers": []
        },
        {
          "name": "Anderson, Brian J.",
          "nameType": "Personal",
          "givenName": "Brian J.",
          "familyName": "Anderson",
          "affiliation": [
            {
              "name": "Applied Physics Laboratory",
              "schemeUri": "https://ror.org",
              "affiliationIdentifier": "https://ror.org/ZZZ",
              "affiliationIdentifierScheme": "ROR"
            }
          ],
          "nameIdentifiers": []
        }
      ],
      "titles": [
        {
          "lang": "en",
          "title": "MESSENGER Magnetometer (MAG) Interplanetary Magnetic Field, Radial-Tangential-Normal, RTN, Coordinates, High Resolution, 1 s Data",
          "titleType": null
        }
      ],
      "publisher": "NASA Space Physics Data Facility",
      "subjects": [
        {
          "subject": "Calibrated"
        },
        {
          "subject": "Ephemeris"
        },
        {
          "subject": "InstrumentStatus"
        },
        {
          "subject": "MagneticField"
        }
      ],
      "contributors": [],
      "dates": [],
      "publicationYear": 2023,
      "language": "en",
      "identifiers": [
        {
          "identifier": "spase://NASA/NumericalData/MESSENGER/MAG/PT0.05S",
          "identifierType": "SPASE"
        }
      ],
      "sizes": [],
      "formats": [
        {
          "subject": "CDF"
        },
        {
          "subject": "CSV"
        }
      ],
      "rightsList": [
        {
          "rights": "Creative Commons Zero v1.0 Universal",
          "rightsUri": "https://creativecommons.org/publicdomain/zero/1.0/legalcode",
          "schemeUri": "https://spdx.org/licenses/",
          "rightsIdentifier": "cc0-1.0",
          "rightsIdentifierScheme": "SPDX"
        }
      ],
      "descriptions": [
        {
          "lang": "en",
          "description": "This MESSENGER Magnetic field data set contains cruise-phase magnetic field vectors in RTN coordinates at time resolutions typically of 0.5 s or 1.0 s and sometimes as fine as 0.05 s.",
          "descriptionType": "Abstract"
        }
      ],
      "geoLocations": [],
      "fundingReferences": [],
      "relatedIdentifiers": [],
      "schemaVersion": "http://datacite.org/schema/kernel-4",
      "providerId": "nasasmd",
      "clientId": "heliophy.spdf",
      "agency": "datacite",
      "state": "draft"
    }
  }
}
